sirius/__init__.py
sirius/__main__.py
sirius/core/__init__.py
sirius/core/request.py
sirius/core/response.py
sirius/routing/__init__.py
sirius/routing/router.py
sirius/sirius.py
sirius/types.py
sirius/utils.py
sirius_api-0.1.2.dist-info/entry_points.txt
sirius_api-0.1.2.dist-info/WHEEL
sirius_api-0.1.2.dist-info/METADATA
sirius_api-0.1.2.dist-info/RECORD
