Metadata-Version: 2.1
Name: sirius-api
Version: 0.1.2
Summary: Create APIs that shine like a star
License: MIT
Author: Vivaan Verma
Author-email: hello@vivaanverma.com
Requires-Python: >=3.10,<4.0
Classifier: License :: OSI Approved :: MIT License
Classifier: Programming Language :: Python :: 3
Classifier: Programming Language :: Python :: 3.10
Requires-Dist: tomli (>=2.0.0,<3.0.0)
Requires-Dist: uvicorn[standard] (>=0.17.1,<0.18.0)
